README.md
setup.py
changelly_api/__init__.py
changelly_api/api.py
changelly_api/exceptions.py
changelly_api.egg-info/PKG-INFO
changelly_api.egg-info/SOURCES.txt
changelly_api.egg-info/dependency_links.txt
changelly_api.egg-info/top_level.txt